tokenease/__init__.py
tokenease/core.py
tokenease-0.1.5.dist-info/LICENSE
tokenease-0.1.5.dist-info/METADATA
tokenease-0.1.5.dist-info/WHEEL
tokenease-0.1.5.dist-info/RECORD
