Metadata-Version: 2.1
Name: tokenease
Version: 0.1.5
Summary: A simple and effective tokenizer.
License: MIT
Author: Mayank Nagda
Author-email: nagdamayank05@gmail.com
Requires-Python: >=3.10,<4.0
Classifier: License :: OSI Approved :: MIT License
Classifier: Programming Language :: Python :: 3
Classifier: Programming Language :: Python :: 3.10
Classifier: Programming Language :: Python :: 3.11
Requires-Dist: joblib (>=1.3.2,<2.0.0)
Requires-Dist: scikit-learn (>=1.3.1,<2.0.0)
Requires-Dist: spacy (>=3.6.1,<4.0.0)
Requires-Dist: unidecode (>=1.3.8,<2.0.0)
